README.rst
setup.py
adapay/__init__.py
adapay/account.py
adapay/adapay_tools.py
adapay/checkout.py
adapay/common.py
adapay/corp_member.py
adapay/drawcash.py
adapay/fast_pay.py
adapay/freeze_account.py
adapay/member.py
adapay/payment.py
adapay/payment_confrim.py
adapay/payment_reverse.py
adapay/refund.py
adapay/request_tools.py
adapay/settle_account.py
adapay/transfer.py
adapay/un_freeze_account.py
adapay/wallet.py
adapay.egg-info/PKG-INFO
adapay.egg-info/SOURCES.txt
adapay.egg-info/dependency_links.txt
adapay.egg-info/requires.txt
adapay.egg-info/top_level.txt