Metadata-Version: 1.1
Name: adapay
Version: 1.3.4
Summary: adapay,an adapter of various pay channels to python server client
Home-page: https://docs.adapay.tech/sdk/pythonsdkaccess.html
Author: adapay developers
Author-email: hi@adapay.tech
License: UNKNOWN
Platform: UNKNOWN
Classifier: Development Status :: 4 - Beta
Classifier: Intended Audience :: Developers
Classifier: Topic :: Software Development :: Build Tools
Classifier: License :: OSI Approved :: MIT License
Classifier: Programming Language :: Python
Classifier: Programming Language :: Python :: 3.5
Classifier: Programming Language :: Python :: 3.6
Classifier: Programming Language :: Python :: 3.7
